pygt1000/__init__.py
pygt1000/constants.py
pygt1000/gt1000.py
pygt1000/specs/Patch.json
pygt1000/specs/Patch.txt
pygt1000/specs/Patch2.json
pygt1000/specs/Patch2.txt
pygt1000/specs/Patch3.json
pygt1000/specs/Patch3.txt
pygt1000/specs/PatchChorus.json
pygt1000/specs/PatchChorus.txt
pygt1000/specs/PatchComp.json
pygt1000/specs/PatchComp.txt
pygt1000/specs/PatchDelay.json
pygt1000/specs/PatchDelay.txt
pygt1000/specs/PatchDist.json
pygt1000/specs/PatchDist.txt
pygt1000/specs/PatchEq.json
pygt1000/specs/PatchEq.txt
pygt1000/specs/PatchFx.json
pygt1000/specs/PatchFx.txt
pygt1000/specs/PatchFxAGSim.json
pygt1000/specs/PatchFxAGSim.txt
pygt1000/specs/PatchFxAWah.json
pygt1000/specs/PatchFxAWah.txt
pygt1000/specs/PatchFxAcReso.json
pygt1000/specs/PatchFxAcReso.txt
pygt1000/specs/PatchFxCVibe.json
pygt1000/specs/PatchFxCVibe.txt
pygt1000/specs/PatchFxChorus.json
pygt1000/specs/PatchFxChorus.txt
pygt1000/specs/PatchFxChorusBass.json
pygt1000/specs/PatchFxChorusBass.txt
pygt1000/specs/PatchFxComp.json
pygt1000/specs/PatchFxComp.txt
pygt1000/specs/PatchFxDefretter.json
pygt1000/specs/PatchFxDefretter.txt
pygt1000/specs/PatchFxDefretterBass.json
pygt1000/specs/PatchFxDefretterBass.txt
pygt1000/specs/PatchFxDist.json
pygt1000/specs/PatchFxDist.txt
pygt1000/specs/PatchFxFeedbacker.json
pygt1000/specs/PatchFxFeedbacker.txt
pygt1000/specs/PatchFxFlanger.json
pygt1000/specs/PatchFxFlanger.txt
pygt1000/specs/PatchFxFlangerBass.json
pygt1000/specs/PatchFxFlangerBass.txt
pygt1000/specs/PatchFxHarmonist.json
pygt1000/specs/PatchFxHarmonist.txt
pygt1000/specs/PatchFxHumanizer.json
pygt1000/specs/PatchFxHumanizer.txt
pygt1000/specs/PatchFxMasteringFx.json
pygt1000/specs/PatchFxMasteringFx.txt
pygt1000/specs/PatchFxOctave.json
pygt1000/specs/PatchFxOctave.txt
pygt1000/specs/PatchFxOctaveBass.json
pygt1000/specs/PatchFxOctaveBass.txt
pygt1000/specs/PatchFxOvertone.json
pygt1000/specs/PatchFxOvertone.txt
pygt1000/specs/PatchFxPan.json
pygt1000/specs/PatchFxPan.txt
pygt1000-0.2.0.dist-info/LICENSE
pygt1000-0.2.0.dist-info/METADATA
pygt1000-0.2.0.dist-info/WHEEL
pygt1000-0.2.0.dist-info/RECORD
