Metadata-Version: 2.1
Name: pygt1000
Version: 0.2.0
Summary: Library to interact with a Boss GT-1000/GT-1000CORE over MIDI
Home-page: https://github.com/jdesfossez/pygt1000
License: MIT
Keywords: midi,boss,gt1000,gt-1000,gt-1000core,guitar,bass
Author: Julien Desfossez
Author-email: j@jdfz.org
Requires-Python: >=3.10,<4.0
Classifier: License :: OSI Approved :: MIT License
Classifier: Programming Language :: Python :: 3
Classifier: Programming Language :: Python :: 3.10
Classifier: Programming Language :: Python :: 3.11
Classifier: Programming Language :: Python :: 3.12
Requires-Dist: python-rtmidi (>=1.5.8,<2.0.0)
Project-URL: Repository, https://github.com/jdesfossez/pygt1000
